[1,["3f077a0d-12ee-4b83-bfe7-a75fd683bee9@6c48a"],["_textureSource"],["cc.SpriteFrame"],0,[{"name":"attack1","rect":{"x":38,"y":72,"width":436,"height":56},"offset":{"x":0,"y":-36},"originalSize":{"width":512,"height":128},"rotated":false,"capInsets":[0,0,0,0],"vertices":{"rawPosition":[-218,-28,0,218,-28,0,-218,28,0,218,28,0],"indexes":[0,1,2,2,1,3],"uv":[38,56,474,56,38,0,474,0],"nuv":[0.07421875,0,0.92578125,0,0.07421875,0.4375,0.92578125,0.4375],"minPos":{"x":-218,"y":-28,"z":0},"maxPos":{"x":218,"y":28,"z":0}},"packable":true,"pixelsToUnit":100,"pivot":{"x":0.5,"y":0.5},"meshType":0}],[0],0,[0],[0],[0]]
