[1,["1dd848a1-fd6c-4034-95f5-a15711dfcef3@6c48a"],["_textureSource"],["cc.SpriteFrame"],0,[{"name":"run1","rect":{"x":25,"y":34,"width":525,"height":62},"offset":{"x":-0.5,"y":-17},"originalSize":{"width":576,"height":96},"rotated":false,"capInsets":[0,0,0,0],"vertices":{"rawPosition":[-262.5,-31,0,262.5,-31,0,-262.5,31,0,262.5,31,0],"indexes":[0,1,2,2,1,3],"uv":[25,62,550,62,25,0,550,0],"nuv":[0.043402777777777776,0,0.9548611111111112,0,0.043402777777777776,0.6458333333333334,0.9548611111111112,0.6458333333333334],"minPos":{"x":-262.5,"y":-31,"z":0},"maxPos":{"x":262.5,"y":31,"z":0}},"packable":true,"pixelsToUnit":100,"pivot":{"x":0.5,"y":0.5},"meshType":0}],[0],0,[0],[0],[0]]
