[1,["ae8d7807-2823-4327-a1fb-2bd3697992ce@6c48a"],["_textureSource"],["cc.SpriteFrame"],0,[{"name":"walk1","rect":{"x":39,"y":50,"width":1457,"height":78},"offset":{"x":-0.5,"y":-25},"originalSize":{"width":1536,"height":128},"rotated":false,"capInsets":[0,0,0,0],"vertices":{"rawPosition":[-728.5,-39,0,728.5,-39,0,-728.5,39,0,728.5,39,0],"indexes":[0,1,2,2,1,3],"uv":[39,78,1496,78,39,0,1496,0],"nuv":[0.025390625,0,0.9739583333333334,0,0.025390625,0.609375,0.9739583333333334,0.609375],"minPos":{"x":-728.5,"y":-39,"z":0},"maxPos":{"x":728.5,"y":39,"z":0}},"packable":true,"pixelsToUnit":100,"pivot":{"x":0.5,"y":0.5},"meshType":0}],[0],0,[0],[0],[0]]
